extractous/__init__.py
extractous/_extractous.abi3.so
extractous/libtika_native.dylib
extractous-0.3.0.dist-info/METADATA
extractous-0.3.0.dist-info/WHEEL
extractous-0.3.0.dist-info/RECORD
