Metadata-Version: 2.4
Name: extractous
Version: 0.3.0
Classifier: Programming Language :: Rust
Classifier: Programming Language :: Python :: Implementation :: CPython
Classifier: Programming Language :: Python :: Implementation :: PyPy
Requires-Dist: pdoc ; extra == 'docs'
Requires-Dist: pytest ; extra == 'test'
Requires-Dist: scikit-learn ; extra == 'test'
Provides-Extra: docs
Provides-Extra: test
Summary: Extractous Python Binding
Home-Page: https://extractous.yobix.ai/
Author: Yobix AI <dev@yobix.ai>
Author-email: Yobix AI <dev@yobix.ai>
License: Apache-2.0
Requires-Python: >=3.8, <3.14
Project-URL: Documentation, https://extractous.yobix.ai/docs/python/index.html
Project-URL: Homepage, https://extractous.yobix.ai/
Project-URL: Repository, https://github.com/yobix-ai/extractous
